cmip_ref_metrics_ilamb/__init__.py
cmip_ref_metrics_ilamb/datasets.py
cmip_ref_metrics_ilamb/py.typed
cmip_ref_metrics_ilamb/standard.py
cmip_ref_metrics_ilamb/configure/ilamb.yaml
cmip_ref_metrics_ilamb/configure/iomb.yaml
cmip_ref_metrics_ilamb/dataset_registry/ilamb.txt
cmip_ref_metrics_ilamb/dataset_registry/iomb.txt
cmip_ref_metrics_ilamb/dataset_registry/test.txt
cmip_ref_metrics_ilamb-0.4.1.dist-info/METADATA
cmip_ref_metrics_ilamb-0.4.1.dist-info/WHEEL
cmip_ref_metrics_ilamb-0.4.1.dist-info/licenses/LICENCE
cmip_ref_metrics_ilamb-0.4.1.dist-info/licenses/NOTICE
cmip_ref_metrics_ilamb-0.4.1.dist-info/RECORD
