Metadata-Version: 2.4
Name: cmip_ref_metrics_ilamb
Version: 0.4.1
Summary: ILAMB metrics provider for the CMIP Rapid Evaluation Framework
Author-email: Nathan Collier <nathaniel.collier@gmail.com>
License: Apache-2.0
License-File: LICENCE
License-File: NOTICE
Classifier: Development Status :: 4 - Beta
Classifier: Intended Audience :: Developers
Classifier: Intended Audience :: Science/Research
Classifier: Operating System :: OS Independent
Classifier: Programming Language :: Python
Classifier: Programming Language :: Python :: 3
Classifier: Programming Language :: Python :: 3.11
Classifier: Programming Language :: Python :: 3.12
Classifier: Programming Language :: Python :: 3.13
Classifier: Topic :: Scientific/Engineering
Requires-Python: >=3.11
Requires-Dist: cmip-ref-core
Requires-Dist: ilamb3
Requires-Dist: types-pyyaml>=6.0.12.20241230
